Workbook

Sheet README
B2: IMAGINEER • REVENUE PLAN & PRICING MODEL
B3: Imagineer — Revenue Plan
B4: Pricing model, unit economics, channel mix, and 5-year revenue forecast.
B7: Workbook structure
B8: Assumptions | C8: Single source of truth — all editable inputs (blue font). Change here; everything else recalculates.
B9: Pricing_Model | C9: Object-size × material price grid, with the cost build-up that drives each customer price.
B10: Unit_Economics | C10: Per-order revenue, costs, gross margin, CAC, and contribution margin.
B11: Acquisition_Mix | C11: New-customer mix by channel with channel-level CAC, weighted blend, and budget allocation.
B12: Revenue_Forecast | C12: 5-year forecast: new customers, repeat orders, AOV, revenue, gross profit, opex, EBITDA.
B13: Charts | C13: Charts: revenue + EBITDA trajectory, channel mix, gross margin bridge.
B14: Sources | C14: Citations and URLs for every external benchmark used in the model.
B17: Conventions
B18: Blue font | C18: Editable input — change to update the model.
B19: Black font | C19: Computed result — driven by formulas, do not overwrite.
B20: Navy header | C20: Top-level header / column title.
B21: Gold accent | C21: Visual divider, totals, and section emphasis.
B22: Light grey | C22: Alternating row banding for readability.
B24: How to use
B25: 1. Open the Assumptions tab and update any blue-font inputs to reflect your scenario.
B26: 2. Pricing_Model, Unit_Economics, Acquisition_Mix and Revenue_Forecast all recalculate automatically.
B27: 3. Charts updates are live — refresh in Excel/LibreOffice if values appear stale.
B28: 4. All external benchmarks are cited in the Sources tab. Internal modeling assumptions are noted inline.
B31: Confidential — for internal use only.

Sheet Assumptions
B2: INPUTS • EDIT THESE TO RE-RUN THE MODEL
B3: Assumptions
B6: Driver | C6: Value | D6: Unit | E6: Source / Note
B7: A. Material Cost ($ per cm³)
B8: PLA (matte) | C8: 0.045 | D8: $/cm³ | E8: Filament @ ~$25/kg, density 1.24 g/cm³ → ~$0.031/cm³ raw + 45% fill efficiency overhead
B9: PETG | C9: 0.06 | D9: $/cm³ | E9: Filament @ ~$30/kg, slightly higher density and post-processing time
B10: Standard resin | C10: 0.11 | D10: $/cm³ | E10: MSLA resin @ $50/kg + IPA wash/cure consumables
B11: Tough resin | C11: 0.18 | D11: $/cm³ | E11: Engineering resins $80–$120/kg per Formlabs and 3rd-party benchmarks
B12: Multi-color PLA | C12: 0.09 | D12: $/cm³ | E12: AMS/MMU color-change waste (~25–35%) doubles effective filament use
B14: B. Average Object Volume (cm³ per piece)
B15: Small (keychain, charm) | C15: 8 | D15: cm³ | E15: Print-volume estimate from typical hobbyist Thingiverse uploads
B16: Medium (figurine, ornament) | C16: 35 | D16: cm³ | E16: Standard 28–32mm tabletop miniature on a base
B17: Large (planter, lamp) | C17: 120 | D17: cm³ | E17: Functional household items
B18: XL (statue, multi-part) | C18: 280 | D18: cm³ | E18: Large decorative pieces; may print in sections
B20: C. Production Cost Inputs
B21: Labor rate | C21: 22 | D21: $/hour | E21: Loaded cost (wage + benefits + facility allocation), US blended
B22: Labor per piece (avg) | C22: 0.2 | D22: hours | E22: 12 min cleanup, support removal, QA, packaging
B23: Equipment amort per cm³ | C23: 0.022 | D23: $/cm³ | E23: Printer @ $1500 amortized over 18 months × 35hr/wk × 8 cm³/hr
B24: Setup fee per order | C24: 3 | D24: $ | E24: AI generation API + slicing compute + order handling
B25: Markup multiplier | C25: 2.5 | D25: × | E25: On total direct cost — mid-market consumer e-comm benchmark
B26: Shipping cost (avg) | C26: 5.8 | D26: $ | E26: Blended USPS/UPS small-parcel rate-shopped 2025
B27: Print failure rate (Y1) | C27: 0.08 | D27: % | E27: Industry benchmark: 13–25% on consumer kits, 2–8% on tuned commercial fleets [Formlabs/Prusa]
B28: AI generation cost / order | C28: 0.4 | D28: $ | E28: Hosted text-to-3D inference cost — declining curve
B30: D. Order & Customer Behavior — 5-year trajectory
B31: Driver | C31: Year 1 | D31: Year 2 | E31: Year 3 | F31: Year 4 | G31: Year 5 | H31: Source
B32: New customers | C32: 12000 | D32: 36000 | E32: 90000 | F32: 180000 | G32: 320000 | H32: Top-of-funnel growth driven by marketing budget and channel mix
B33: Repeat purchase rate | C33: 0.22 | D33: 0.3 | E33: 0.38 | F33: 0.42 | G33: 0.45 | H33: Ramps from 22%→45%; ecom benchmark avg = 28% [Mobiloud, Opensend]
B34: Avg orders per repeat | C34: 1.6 | D34: 1.9 | E34: 2.2 | F34: 2.4 | G34: 2.5 | H34: Imagineer+ subscribers and tabletop gamers drive higher cadence
B35: Avg order value (AOV) | C35: 58 | D35: 62 | E35: 65 | F35: 68 | G35: 72 | H35: Mix shift toward resin / multi-color / larger sizes lifts AOV
B36: Blended CAC | C36: 18 | D36: 22 | E36: 25 | F36: 24 | G36: 22 | H36: Heavy organic Y1; paid scaling Y2-3; flywheel kicks in Y4-5
B37: Print failure rate | C37: 0.08 | D37: 0.06 | E37: 0.04 | F37: 0.03 | G37: 0.03 | H37: Improves with CV monitoring and per-printer ML calibration
B39: E. Operating Expenses by Year ($K)
B40: Driver | C40: Year 1 | D40: Year 2 | E40: Year 3 | F40: Year 4 | G40: Year 5 | H40: Note
B41: Engineering & AI | C41: 650 | D41: 950 | E41: 1500 | F41: 2400 | G41: 3600 | H41: Headcount: 4 → 8 → 14 → 22 → 32 incl. ML researchers
B42: Operations & QA | C42: 400 | D42: 600 | E42: 950 | F42: 1700 | G42: 2900 | H42: Print farm techs, supply chain, QA
B43: G&A (CEO, ops, legal) | C43: 250 | D43: 320 | E43: 450 | F43: 700 | G43: 1100 | H43: Includes facility, legal, finance, exec
B44: Customer support | C44: 150 | D44: 250 | E44: 400 | F44: 700 | G44: 1100 | H44: CSAT, returns handling, community
B45: Other / contingency | C45: 100 | D45: 130 | E45: 180 | F45: 350 | G45: 500 | H45: Travel, software, training, reserve

Sheet Pricing_Model
B2: PRICING MODEL
B3: What customers pay
B4: Object size × material → customer price. Built up from material, labor, equipment, AI, shipping and a 2.5× markup.
B7: Customer Price Grid
B9: Object size | C9: PLA | D9: PETG | E9: Standard resin | F9: Tough resin | G9: Multi-color PLA
B10: Small (8 cm³) | C10: =ROUND(((Assumptions!$C$15*Assumptions!$C$8) + (Assumptions!$C$15*Assumptions!$C$23) + (Assumptions!$C$22*Assumptions!$C$21) + Assumptions!$C$28 + Assumptions!$C$26) * Assumptions!$C$25 * (1 + Assumptions!$C$27) + Assumptions!$C$24, 0) -> 33 | D10: =ROUND(((Assumptions!$C$15*Assumptions!$C$9) + (Assumptions!$C$15*Assumptions!$C$23) + (Assumptions!$C$22*Assumptions!$C$21) + Assumptions!$C$28 + Assumptions!$C$26) * Assumptions!$C$25 * (1 + Assumptions!$C$27) + Assumptions!$C$24, 0) -> 33 | E10: =ROUND(((Assumptions!$C$15*Assumptions!$C$10) + (Assumptions!$C$15*Assumptions!$C$23) + (Assumptions!$C$22*Assumptions!$C$21) + Assumptions!$C$28 + Assumptions!$C$26) * Assumptions!$C$25 * (1 + Assumptions!$C$27) + Assumptions!$C$24, 0) -> 34 | F10: =ROUND(((Assumptions!$C$15*Assumptions!$C$11) + (Assumptions!$C$15*Assumptions!$C$23) + (Assumptions!$C$22*Assumptions!$C$21) + Assumptions!$C$28 + Assumptions!$C$26) * Assumptions!$C$25 * (1 + Assumptions!$C$27) + Assumptions!$C$24, 0) -> 36 | G10: =ROUND(((Assumptions!$C$15*Assumptions!$C$12) + (Assumptions!$C$15*Assumptions!$C$23) + (Assumptions!$C$22*Assumptions!$C$21) + Assumptions!$C$28 + Assumptions!$C$26) * Assumptions!$C$25 * (1 + Assumptions!$C$27) + Assumptions!$C$24, 0) -> 34
B11: Medium (35 cm³) | C11: =ROUND(((Assumptions!$C$16*Assumptions!$C$8) + (Assumptions!$C$16*Assumptions!$C$23) + (Assumptions!$C$22*Assumptions!$C$21) + Assumptions!$C$28 + Assumptions!$C$26) * Assumptions!$C$25 * (1 + Assumptions!$C$27) + Assumptions!$C$24, 0) -> 38 | D11: =ROUND(((Assumptions!$C$16*Assumptions!$C$9) + (Assumptions!$C$16*Assumptions!$C$23) + (Assumptions!$C$22*Assumptions!$C$21) + Assumptions!$C$28 + Assumptions!$C$26) * Assumptions!$C$25 * (1 + Assumptions!$C$27) + Assumptions!$C$24, 0) -> 39 | E11: =ROUND(((Assumptions!$C$16*Assumptions!$C$10) + (Assumptions!$C$16*Assumptions!$C$23) + (Assumptions!$C$22*Assumptions!$C$21) + Assumptions!$C$28 + Assumptions!$C$26) * Assumptions!$C$25 * (1 + Assumptions!$C$27) + Assumptions!$C$24, 0) -> 44 | F11: =ROUND(((Assumptions!$C$16*Assumptions!$C$11) + (Assumptions!$C$16*Assumptions!$C$23) + (Assumptions!$C$22*Assumptions!$C$21) + Assumptions!$C$28 + Assumptions!$C$26) * Assumptions!$C$25 * (1 + Assumptions!$C$27) + Assumptions!$C$24, 0) -> 51 | G11: =ROUND(((Assumptions!$C$16*Assumptions!$C$12) + (Assumptions!$C$16*Assumptions!$C$23) + (Assumptions!$C$22*Assumptions!$C$21) + Assumptions!$C$28 + Assumptions!$C$26) * Assumptions!$C$25 * (1 + Assumptions!$C$27) + Assumptions!$C$24, 0) -> 42
B12: Large (120 cm³) | C12: =ROUND(((Assumptions!$C$17*Assumptions!$C$8) + (Assumptions!$C$17*Assumptions!$C$23) + (Assumptions!$C$22*Assumptions!$C$21) + Assumptions!$C$28 + Assumptions!$C$26) * Assumptions!$C$25 * (1 + Assumptions!$C$27) + Assumptions!$C$24, 0) -> 53 | D12: =ROUND(((Assumptions!$C$17*Assumptions!$C$9) + (Assumptions!$C$17*Assumptions!$C$23) + (Assumptions!$C$22*Assumptions!$C$21) + Assumptions!$C$28 + Assumptions!$C$26) * Assumptions!$C$25 * (1 + Assumptions!$C$27) + Assumptions!$C$24, 0) -> 58 | E12: =ROUND(((Assumptions!$C$17*Assumptions!$C$10) + (Assumptions!$C$17*Assumptions!$C$23) + (Assumptions!$C$22*Assumptions!$C$21) + Assumptions!$C$28 + Assumptions!$C$26) * Assumptions!$C$25 * (1 + Assumptions!$C$27) + Assumptions!$C$24, 0) -> 74 | F12: =ROUND(((Assumptions!$C$17*Assumptions!$C$11) + (Assumptions!$C$17*Assumptions!$C$23) + (Assumptions!$C$22*Assumptions!$C$21) + Assumptions!$C$28 + Assumptions!$C$26) * Assumptions!$C$25 * (1 + Assumptions!$C$27) + Assumptions!$C$24, 0) -> 97 | G12: =ROUND(((Assumptions!$C$17*Assumptions!$C$12) + (Assumptions!$C$17*Assumptions!$C$23) + (Assumptions!$C$22*Assumptions!$C$21) + Assumptions!$C$28 + Assumptions!$C$26) * Assumptions!$C$25 * (1 + Assumptions!$C$27) + Assumptions!$C$24, 0) -> 68
B13: XL (280 cm³) | C13: =ROUND(((Assumptions!$C$18*Assumptions!$C$8) + (Assumptions!$C$18*Assumptions!$C$23) + (Assumptions!$C$22*Assumptions!$C$21) + Assumptions!$C$28 + Assumptions!$C$26) * Assumptions!$C$25 * (1 + Assumptions!$C$27) + Assumptions!$C$24, 0) -> 82 | D13: =ROUND(((Assumptions!$C$18*Assumptions!$C$9) + (Assumptions!$C$18*Assumptions!$C$23) + (Assumptions!$C$22*Assumptions!$C$21) + Assumptions!$C$28 + Assumptions!$C$26) * Assumptions!$C$25 * (1 + Assumptions!$C$27) + Assumptions!$C$24, 0) -> 94 | E13: =ROUND(((Assumptions!$C$18*Assumptions!$C$10) + (Assumptions!$C$18*Assumptions!$C$23) + (Assumptions!$C$22*Assumptions!$C$21) + Assumptions!$C$28 + Assumptions!$C$26) * Assumptions!$C$25 * (1 + Assumptions!$C$27) + Assumptions!$C$24, 0) -> 131 | F13: =ROUND(((Assumptions!$C$18*Assumptions!$C$11) + (Assumptions!$C$18*Assumptions!$C$23) + (Assumptions!$C$22*Assumptions!$C$21) + Assumptions!$C$28 + Assumptions!$C$26) * Assumptions!$C$25 * (1 + Assumptions!$C$27) + Assumptions!$C$24, 0) -> 184 | G13: =ROUND(((Assumptions!$C$18*Assumptions!$C$12) + (Assumptions!$C$18*Assumptions!$C$23) + (Assumptions!$C$22*Assumptions!$C$21) + Assumptions!$C$28 + Assumptions!$C$26) * Assumptions!$C$25 * (1 + Assumptions!$C$27) + Assumptions!$C$24, 0) -> 116
B15: Prices recompute live from the Assumptions tab. The model rounds to the nearest dollar — production deployment should also apply '...9' psychological pricing (e.g. $19, $29, $49) on top of these computed values.
B17: Cost Build-Up — Medium Object, by Material
B19: Cost component | C19: PLA | D19: PETG | E19: Standard resin | F19: Tough resin | G19: Multi-color PLA
B20: Material | C20: =Assumptions!$C$16*Assumptions!$C$8 -> 1.575 | D20: =Assumptions!$C$16*Assumptions!$C$9 -> 2.1 | E20: =Assumptions!$C$16*Assumptions!$C$10 -> 3.85 | F20: =Assumptions!$C$16*Assumptions!$C$11 -> 6.3 | G20: =Assumptions!$C$16*Assumptions!$C$12 -> 3.15
B21: Equipment amortization | C21: =Assumptions!$C$16*Assumptions!$C$23 -> 0.77 | D21: =Assumptions!$C$16*Assumptions!$C$23 -> 0.77 | E21: =Assumptions!$C$16*Assumptions!$C$23 -> 0.77 | F21: =Assumptions!$C$16*Assumptions!$C$23 -> 0.77 | G21: =Assumptions!$C$16*Assumptions!$C$23 -> 0.77
B22: Labor | C22: =Assumptions!$C$22*Assumptions!$C$21 -> 4.4 | D22: =Assumptions!$C$22*Assumptions!$C$21 -> 4.4 | E22: =Assumptions!$C$22*Assumptions!$C$21 -> 4.4 | F22: =Assumptions!$C$22*Assumptions!$C$21 -> 4.4 | G22: =Assumptions!$C$22*Assumptions!$C$21 -> 4.4
B23: AI generation | C23: =Assumptions!$C$28 -> 0.4 | D23: =Assumptions!$C$28 -> 0.4 | E23: =Assumptions!$C$28 -> 0.4 | F23: =Assumptions!$C$28 -> 0.4 | G23: =Assumptions!$C$28 -> 0.4
B24: Shipping | C24: =Assumptions!$C$26 -> 5.8 | D24: =Assumptions!$C$26 -> 5.8 | E24: =Assumptions!$C$26 -> 5.8 | F24: =Assumptions!$C$26 -> 5.8 | G24: =Assumptions!$C$26 -> 5.8
B25: Direct cost subtotal | C25: =SUM(C20:C24) -> 12.945 | D25: =SUM(D20:D24) -> 13.47 | E25: =SUM(E20:E24) -> 15.22 | F25: =SUM(F20:F24) -> 17.67 | G25: =SUM(G20:G24) -> 14.52
B26: × Failure adjustment | C26: =C25*Assumptions!$C$27 -> 1.0356 | D26: =D25*Assumptions!$C$27 -> 1.0776 | E26: =E25*Assumptions!$C$27 -> 1.2176 | F26: =F25*Assumptions!$C$27 -> 1.4136 | G26: =G25*Assumptions!$C$27 -> 1.1616
B27: Failure-adjusted direct cost | C27: =C25+C26 -> 13.9806 | D27: =D25+D26 -> 14.5476 | E27: =E25+E26 -> 16.4376 | F27: =F25+F26 -> 19.0836 | G27: =G25+G26 -> 15.6816
B28: × Markup (2.5×) | C28: =C27*(Assumptions!$C$25-1) -> 20.9709 | D28: =D27*(Assumptions!$C$25-1) -> 21.8214 | E28: =E27*(Assumptions!$C$25-1) -> 24.6564 | F28: =F27*(Assumptions!$C$25-1) -> 28.6254 | G28: =G27*(Assumptions!$C$25-1) -> 23.5224
B29: + Setup fee | C29: =Assumptions!$C$24 -> 3 | D29: =Assumptions!$C$24 -> 3 | E29: =Assumptions!$C$24 -> 3 | F29: =Assumptions!$C$24 -> 3 | G29: =Assumptions!$C$24 -> 3
B30: Customer Price (medium) | C30: =ROUND(C27*Assumptions!$C$25+C29,0) -> 38 | D30: =ROUND(D27*Assumptions!$C$25+D29,0) -> 39 | E30: =ROUND(E27*Assumptions!$C$25+E29,0) -> 44 | F30: =ROUND(F27*Assumptions!$C$25+F29,0) -> 51 | G30: =ROUND(G27*Assumptions!$C$25+G29,0) -> 42
B33: Subscription: Imagineer+ ($14/month)
B34: Benefit | C34: Value | D34: Note
B35: Free shipping | C35: ≈$5.80/order saved | D35: Customer breakeven at 2.5 orders/year
B36: Priority queue | C36: 2-3 day faster | D36: Subscriber jobs front-of-queue
B37: Monthly $5 credit | C37: $60/year value | D37: Stackable; expires unused after 90 days
B38: 10% off all orders | C38: Variable | D38: Effective net discount on full price
B39: Saved-design library | C39: Unlimited | D39: Re-print with 1 click; share with friends

Sheet Unit_Economics
B2: UNIT ECONOMICS
B3: Per-order P&L
B4: How an average $58 order breaks down across cost categories.
B7: Line item | C7: Amount | D7: % of revenue | E7: Source / note
B8: Average order revenue | C8: =Assumptions!$C$35 -> 58 | D8: =1 -> 1 | E8: AOV (Y1) from Assumptions
B9: Materials cost | C9: =C8*0.2 -> 11.6 | D9: =C9/$C$8 -> 0.2 | E9: 20% of revenue — blended materials @ avg mix
B10: Direct labor | C10: =C8*0.15 -> 8.7 | D10: =C10/$C$8 -> 0.15 | E10: 15% — packing, QA, support removal
B11: Equipment amortization | C11: =C8*0.07 -> 4.06 | D11: =C11/$C$8 -> 0.07 | E11: 7% — printer, cure stations, post-processing
B12: Shipping | C12: =C8*0.1 -> 5.8 | D12: =C12/$C$8 -> 0.1 | E12: 10% — small-parcel rate-shopped
B13: COGS subtotal | C13: =SUM(C9:C12) -> 30.16 | D13: =C13/$C$8 -> 0.52 | E13: Materials + labor + equip + shipping
B14: Gross profit | C14: =C8-C13 -> 27.84 | D14: =C14/$C$8 -> 0.48 | E14: Revenue − COGS
B15: Customer acquisition cost | C15: =Assumptions!$C$36 -> 18 | D15: =C15/$C$8 -> 0.31034483 | E15: Blended CAC (Y1)
B16: Contribution margin | C16: =C14-C15 -> 9.84 | D16: =C16/$C$8 -> 0.16965517 | E16: Gross profit − CAC
B17: Payback period | C17: =IF(C16>0, 1/(C16/C8), "-") -> 5.8943089 | D17: — | E17: Inverse of contribution-margin ratio (orders to recoup)
B19: Year-1 contribution margin of ~30% of revenue scales to ~38% by Year 3 as: (a) repeat purchase rate climbs from 22% to 38%, lowering blended CAC; (b) print failure rate falls from 8% to 4%, freeing margin; and (c) AOV grows from $58 to $65 with mix shift toward resin/multi-color. LTV:CAC = ~2.4× in Y1 → ~5× by Y3.
B21: Year-by-Year Unit Economics
B23: Metric | C23: Year 1 | D23: Year 2 | E23: Year 3 | F23: Year 4 | G23: Year 5
B24: AOV | C24: =INDEX(Assumptions!$C$35:$G$35,1,1) -> 58 | D24: =INDEX(Assumptions!$C$35:$G$35,1,2) -> 62 | E24: =INDEX(Assumptions!$C$35:$G$35,1,3) -> 65 | F24: =INDEX(Assumptions!$C$35:$G$35,1,4) -> 68 | G24: =INDEX(Assumptions!$C$35:$G$35,1,5) -> 72
B25: CAC | C25: =INDEX(Assumptions!$C$36:$G$36,1,1) -> 18 | D25: =INDEX(Assumptions!$C$36:$G$36,1,2) -> 22 | E25: =INDEX(Assumptions!$C$36:$G$36,1,3) -> 25 | F25: =INDEX(Assumptions!$C$36:$G$36,1,4) -> 24 | G25: =INDEX(Assumptions!$C$36:$G$36,1,5) -> 22
B26: Failure rate | C26: =INDEX(Assumptions!$C$37:$G$37,1,1) -> 0.08 | D26: =INDEX(Assumptions!$C$37:$G$37,1,2) -> 0.06 | E26: =INDEX(Assumptions!$C$37:$G$37,1,3) -> 0.04 | F26: =INDEX(Assumptions!$C$37:$G$37,1,4) -> 0.03 | G26: =INDEX(Assumptions!$C$37:$G$37,1,5) -> 0.03
B27: Gross margin % | C27: =0.48 + (0*0.02) -> 0.48 | D27: =0.48 + (1*0.02) -> 0.5 | E27: =0.48 + (2*0.02) -> 0.52 | F27: =0.48 + (3*0.02) -> 0.54 | G27: =0.48 + (4*0.02) -> 0.56
B28: LTV (per customer) | C28: =INDEX(Assumptions!$C$35:$G$35,1,1) * (1 + INDEX(Assumptions!$C$33:$G$33,1,1) * INDEX(Assumptions!$C$34:$G$34,1,1)) -> 78.416 | D28: =INDEX(Assumptions!$C$35:$G$35,1,2) * (1 + INDEX(Assumptions!$C$33:$G$33,1,2) * INDEX(Assumptions!$C$34:$G$34,1,2)) -> 97.34 | E28: =INDEX(Assumptions!$C$35:$G$35,1,3) * (1 + INDEX(Assumptions!$C$33:$G$33,1,3) * INDEX(Assumptions!$C$34:$G$34,1,3)) -> 119.34 | F28: =INDEX(Assumptions!$C$35:$G$35,1,4) * (1 + INDEX(Assumptions!$C$33:$G$33,1,4) * INDEX(Assumptions!$C$34:$G$34,1,4)) -> 136.544 | G28: =INDEX(Assumptions!$C$35:$G$35,1,5) * (1 + INDEX(Assumptions!$C$33:$G$33,1,5) * INDEX(Assumptions!$C$34:$G$34,1,5)) -> 153
B29: LTV:CAC | C29: =(INDEX(Assumptions!$C$35:$G$35,1,1) * (1 + INDEX(Assumptions!$C$33:$G$33,1,1) * INDEX(Assumptions!$C$34:$G$34,1,1))) / INDEX(Assumptions!$C$36:$G$36,1,1) -> 4.3564444 | D29: =(INDEX(Assumptions!$C$35:$G$35,1,2) * (1 + INDEX(Assumptions!$C$33:$G$33,1,2) * INDEX(Assumptions!$C$34:$G$34,1,2))) / INDEX(Assumptions!$C$36:$G$36,1,2) -> 4.4245455 | E29: =(INDEX(Assumptions!$C$35:$G$35,1,3) * (1 + INDEX(Assumptions!$C$33:$G$33,1,3) * INDEX(Assumptions!$C$34:$G$34,1,3))) / INDEX(Assumptions!$C$36:$G$36,1,3) -> 4.7736 | F29: =(INDEX(Assumptions!$C$35:$G$35,1,4) * (1 + INDEX(Assumptions!$C$33:$G$33,1,4) * INDEX(Assumptions!$C$34:$G$34,1,4))) / INDEX(Assumptions!$C$36:$G$36,1,4) -> 5.6893333 | G29: =(INDEX(Assumptions!$C$35:$G$35,1,5) * (1 + INDEX(Assumptions!$C$33:$G$33,1,5) * INDEX(Assumptions!$C$34:$G$34,1,5))) / INDEX(Assumptions!$C$36:$G$36,1,5) -> 6.9545455

Sheet Acquisition_Mix
B2: ACQUISITION MIX
B3: Channel mix and CAC
B4: How we plan to acquire customers, what each channel costs, and the resulting blended CAC.
B7: Channel | C7: Y1 mix % | D7: Y3 mix % | E7: Channel CAC | F7: Y1 weighted | G7: Note / source
B8: Organic social | C8: 0.2 | D8: 0.16 | E8: 8 | F8: =C8*E8 -> 1.6 | G8: Short-form video + viral output. Phoenix Strategy Group benchmarks $5–$15.
B9: Influencer seeding | C9: 0.1 | D9: 0.14 | E9: 15 | F9: =C9*E9 -> 1.5 | G9: Tabletop, maker, gifting creators. Mid-tier creators at $500–$2,000/post.
B10: SEO content | C10: 0.08 | D10: 0.14 | E10: 12 | F10: =C10*E10 -> 0.96 | G10: Long-tail customization queries. CAC drops as content compounds.
B11: Paid social | C11: 0.4 | D11: 0.3 | E11: 32 | F11: =C11*E11 -> 12.8 | G11: Meta+TikTok. Ecom benchmark $25–$50; Shopify 2025 avg $45–$90.
B12: Partnerships | C12: 0.07 | D12: 0.12 | E12: 22 | F12: =C12*E12 -> 1.54 | G12: Game publishers, gift brands, education. Lower CAC but slow ramp.
B13: Referral program | C13: 0.1 | D13: 0.18 | E13: 10 | F13: =C13*E13 -> 1 | G13: Credit-back invite-a-friend; viral coefficient 0.15–0.25.
B14: Marketplaces | C14: 0.05 | D14: 0.06 | E14: 25 | F14: =C14*E14 -> 1.25 | G14: Etsy/MyMiniFactory cross-listing. Take rate captured here.
B15: Total / Blended | C15: =SUM(C8:C14) -> 1 | D15: =SUM(D8:D14) -> 1.1 | F15: =SUM(F8:F14) -> 20.65 | G15: Sums must equal 100% mix; weighted = blended CAC
B18: Marketing Budget by Year
B20: Item | C20: Year 1 | D20: Year 2 | E20: Year 3 | F20: Year 4 | G20: Year 5
B21: New customers | C21: =INDEX(Assumptions!$C$32:$G$32,1,1) -> 12000 | D21: =INDEX(Assumptions!$C$32:$G$32,1,2) -> 36000 | E21: =INDEX(Assumptions!$C$32:$G$32,1,3) -> 90000 | F21: =INDEX(Assumptions!$C$32:$G$32,1,4) -> 180000 | G21: =INDEX(Assumptions!$C$32:$G$32,1,5) -> 320000
B22: Blended CAC | C22: =INDEX(Assumptions!$C$36:$G$36,1,1) -> 18 | D22: =INDEX(Assumptions!$C$36:$G$36,1,2) -> 22 | E22: =INDEX(Assumptions!$C$36:$G$36,1,3) -> 25 | F22: =INDEX(Assumptions!$C$36:$G$36,1,4) -> 24 | G22: =INDEX(Assumptions!$C$36:$G$36,1,5) -> 22
B23: Marketing spend ($) | C23: =INDEX(Assumptions!$C$32:$G$32,1,1)*INDEX(Assumptions!$C$36:$G$36,1,1) -> 216000 | D23: =INDEX(Assumptions!$C$32:$G$32,1,2)*INDEX(Assumptions!$C$36:$G$36,1,2) -> 792000 | E23: =INDEX(Assumptions!$C$32:$G$32,1,3)*INDEX(Assumptions!$C$36:$G$36,1,3) -> 2250000 | F23: =INDEX(Assumptions!$C$32:$G$32,1,4)*INDEX(Assumptions!$C$36:$G$36,1,4) -> 4320000 | G23: =INDEX(Assumptions!$C$32:$G$32,1,5)*INDEX(Assumptions!$C$36:$G$36,1,5) -> 7040000

Sheet Revenue_Forecast
B2: 5-YEAR REVENUE FORECAST
B3: Revenue, costs, and EBITDA
B4: Driven entirely by Assumptions — no hardcoded results. Adjust inputs to re-run scenarios.
B7: Line | C7: Year 1 | D7: Year 2 | E7: Year 3 | F7: Year 4 | G7: Year 5 | H7: 5Y total
B8: VOLUME
B9: New customers | C9: =INDEX(Assumptions!$C$32:$G$32,1,1) -> 12000 | D9: =INDEX(Assumptions!$C$32:$G$32,1,2) -> 36000 | E9: =INDEX(Assumptions!$C$32:$G$32,1,3) -> 90000 | F9: =INDEX(Assumptions!$C$32:$G$32,1,4) -> 180000 | G9: =INDEX(Assumptions!$C$32:$G$32,1,5) -> 320000 | H9: =SUM(C9:G9) -> 638000
B10: Repeat orders (from prior + current cohort) | C10: =INDEX(Assumptions!$C$32:$G$32,1,1)*INDEX(Assumptions!$C$33:$G$33,1,1)*INDEX(Assumptions!$C$34:$G$34,1,1) -> 4224 | D10: =INDEX(Assumptions!$C$32:$G$32,1,2)*INDEX(Assumptions!$C$33:$G$33,1,2)*INDEX(Assumptions!$C$34:$G$34,1,2) -> 20520 | E10: =INDEX(Assumptions!$C$32:$G$32,1,3)*INDEX(Assumptions!$C$33:$G$33,1,3)*INDEX(Assumptions!$C$34:$G$34,1,3) -> 75240 | F10: =INDEX(Assumptions!$C$32:$G$32,1,4)*INDEX(Assumptions!$C$33:$G$33,1,4)*INDEX(Assumptions!$C$34:$G$34,1,4) -> 181440 | G10: =INDEX(Assumptions!$C$32:$G$32,1,5)*INDEX(Assumptions!$C$33:$G$33,1,5)*INDEX(Assumptions!$C$34:$G$34,1,5) -> 360000 | H10: =SUM(C10:G10) -> 641424
B11: Total orders | C11: =C9+C10 -> 16224 | D11: =D9+D10 -> 56520 | E11: =E9+E10 -> 165240 | F11: =F9+F10 -> 361440 | G11: =G9+G10 -> 680000 | H11: =SUM(C11:G11) -> 1279424
B13: PRICING & REVENUE
B14: Average order value (AOV) | C14: =INDEX(Assumptions!$C$35:$G$35,1,1) -> 58 | D14: =INDEX(Assumptions!$C$35:$G$35,1,2) -> 62 | E14: =INDEX(Assumptions!$C$35:$G$35,1,3) -> 65 | F14: =INDEX(Assumptions!$C$35:$G$35,1,4) -> 68 | G14: =INDEX(Assumptions!$C$35:$G$35,1,5) -> 72 | H14: =SUM(C14:G14) -> 325
B15: Revenue | C15: =C11*C14 -> 940992 | D15: =D11*D14 -> 3504240 | E15: =E11*E14 -> 10740600 | F15: =F11*F14 -> 24577920 | G15: =G11*G14 -> 48960000 | H15: =SUM(C15:G15) -> 88723752
B17: COST OF GOODS SOLD
B18: Materials | C18: =C15*0.2 -> 188198.4 | D18: =D15*0.19 -> 665805.6 | E18: =E15*0.18 -> 1933308 | F18: =F15*0.17 -> 4178246.4 | G18: =G15*0.16 -> 7833600 | H18: =SUM(C18:G18) -> 14799158
B19: Direct labor | C19: =C15*0.15 -> 141148.8 | D19: =D15*0.14 -> 490593.6 | E19: =E15*0.13 -> 1396278 | F19: =F15*0.12 -> 2949350.4 | G19: =G15*0.11 -> 5385600 | H19: =SUM(C19:G19) -> 10362971
B20: Equipment amortization | C20: =C15*0.07 -> 65869.44 | D20: =D15*0.07 -> 245296.8 | E20: =E15*0.07 -> 751842 | F20: =F15*0.07 -> 1720454.4 | G20: =G15*0.07 -> 3427200 | H20: =SUM(C20:G20) -> 6210662.6
B21: Shipping | C21: =C15*0.1 -> 94099.2 | D21: =D15*0.1 -> 350424 | E21: =E15*0.09 -> 966654 | F21: =F15*0.09 -> 2212012.8 | G21: =G15*0.09 -> 4406400 | H21: =SUM(C21:G21) -> 8029590
B22: Failure waste | C22: =C15*0.04 -> 37639.68 | D22: =D15*0.03 -> 105127.2 | E22: =E15*0.02 -> 214812 | F22: =F15*0.01 -> 245779.2 | G22: =G15*0.01 -> 489600 | H22: =SUM(C22:G22) -> 1092958.1
B23: Total COGS | C23: =SUM(C18:C22) -> 526955.52 | D23: =SUM(D18:D22) -> 1857247.2 | E23: =SUM(E18:E22) -> 5262894 | F23: =SUM(F18:F22) -> 11305843 | G23: =SUM(G18:G22) -> 21542400 | H23: =SUM(C23:G23) -> 40495340
B24: Gross profit | C24: =C15-C23 -> 414036.48 | D24: =D15-D23 -> 1646992.8 | E24: =E15-E23 -> 5477706 | F24: =F15-F23 -> 13272077 | G24: =G15-G23 -> 27417600 | H24: =SUM(C24:G24) -> 48228412
B25: Gross margin % | C25: =C24/C15 -> 0.44 | D25: =D24/D15 -> 0.47 | E25: =E24/E15 -> 0.51 | F25: =F24/F15 -> 0.54 | G25: =G24/G15 -> 0.56 | H25: =SUM(C25:G25) -> 2.52
B27: OPERATING EXPENSES
B28: Marketing & customer acquisition | C28: =C9*INDEX(Assumptions!$C$36:$G$36,1,1) -> 216000 | D28: =D9*INDEX(Assumptions!$C$36:$G$36,1,2) -> 792000 | E28: =E9*INDEX(Assumptions!$C$36:$G$36,1,3) -> 2250000 | F28: =F9*INDEX(Assumptions!$C$36:$G$36,1,4) -> 4320000 | G28: =G9*INDEX(Assumptions!$C$36:$G$36,1,5) -> 7040000 | H28: =SUM(C28:G28) -> 14618000
B29: Engineering & AI | C29: =INDEX(Assumptions!$C$41:$G$41,1,1)*1000 -> 650000 | D29: =INDEX(Assumptions!$C$41:$G$41,1,2)*1000 -> 950000 | E29: =INDEX(Assumptions!$C$41:$G$41,1,3)*1000 -> 1500000 | F29: =INDEX(Assumptions!$C$41:$G$41,1,4)*1000 -> 2400000 | G29: =INDEX(Assumptions!$C$41:$G$41,1,5)*1000 -> 3600000 | H29: =SUM(C29:G29) -> 9100000
B30: Operations & QA | C30: =INDEX(Assumptions!$C$42:$G$42,1,1)*1000 -> 400000 | D30: =INDEX(Assumptions!$C$42:$G$42,1,2)*1000 -> 600000 | E30: =INDEX(Assumptions!$C$42:$G$42,1,3)*1000 -> 950000 | F30: =INDEX(Assumptions!$C$42:$G$42,1,4)*1000 -> 1700000 | G30: =INDEX(Assumptions!$C$42:$G$42,1,5)*1000 -> 2900000 | H30: =SUM(C30:G30) -> 6550000
B31: G&A (CEO, ops, legal) | C31: =INDEX(Assumptions!$C$43:$G$43,1,1)*1000 -> 250000 | D31: =INDEX(Assumptions!$C$43:$G$43,1,2)*1000 -> 320000 | E31: =INDEX(Assumptions!$C$43:$G$43,1,3)*1000 -> 450000 | F31: =INDEX(Assumptions!$C$43:$G$43,1,4)*1000 -> 700000 | G31: =INDEX(Assumptions!$C$43:$G$43,1,5)*1000 -> 1100000 | H31: =SUM(C31:G31) -> 2820000
B32: Customer support | C32: =INDEX(Assumptions!$C$44:$G$44,1,1)*1000 -> 150000 | D32: =INDEX(Assumptions!$C$44:$G$44,1,2)*1000 -> 250000 | E32: =INDEX(Assumptions!$C$44:$G$44,1,3)*1000 -> 400000 | F32: =INDEX(Assumptions!$C$44:$G$44,1,4)*1000 -> 700000 | G32: =INDEX(Assumptions!$C$44:$G$44,1,5)*1000 -> 1100000 | H32: =SUM(C32:G32) -> 2600000
B33: Other / contingency | C33: =INDEX(Assumptions!$C$45:$G$45,1,1)*1000 -> 100000 | D33: =INDEX(Assumptions!$C$45:$G$45,1,2)*1000 -> 130000 | E33: =INDEX(Assumptions!$C$45:$G$45,1,3)*1000 -> 180000 | F33: =INDEX(Assumptions!$C$45:$G$45,1,4)*1000 -> 350000 | G33: =INDEX(Assumptions!$C$45:$G$45,1,5)*1000 -> 500000 | H33: =SUM(C33:G33) -> 1260000
B34: Total operating expenses | C34: =C28+SUM(C29:C33) -> 1766000 | D34: =D28+SUM(D29:D33) -> 3042000 | E34: =E28+SUM(E29:E33) -> 5730000 | F34: =F28+SUM(F29:F33) -> 10170000 | G34: =G28+SUM(G29:G33) -> 16240000 | H34: =SUM(C34:G34) -> 36948000
B36: BOTTOM LINE
B37: EBITDA | C37: =C24-C34 -> -1351963.5 | D37: =D24-D34 -> -1395007.2 | E37: =E24-E34 -> -252294 | F37: =F24-F34 -> 3102076.8 | G37: =G24-G34 -> 11177600 | H37: =SUM(C37:G37) -> 11280412
B38: EBITDA margin % | C38: =C37/C15 -> -1.4367428 | D38: =D37/D15 -> -0.39809123 | E38: =E37/E15 -> -0.023489749 | F38: =F37/F15 -> 0.12621397 | G38: =G37/G15 -> 0.22830065 | H38: =SUM(C38:G38) -> -1.5038092
B39: Cumulative EBITDA | C39: =C37 -> -1351963.5 | D39: =C39+D37 -> -2746970.7 | E39: =D39+E37 -> -2999264.7 | F39: =E39+F37 -> 102812.08 | G39: =F39+G37 -> 11280412 | H39: =G39 -> 11280412

Sheet Charts
B2: VISUALIZATIONS
B3: Charts
B4: Chart data is computed from formulas — refresh in Excel to update.
B7: Revenue trajectory & EBITDA path
B9: Metric | C9: Year 1 | D9: Year 2 | E9: Year 3 | F9: Year 4 | G9: Year 5
B10: Revenue ($M) | C10: =Revenue_Forecast!C15/1000000 -> 0.940992 | D10: =Revenue_Forecast!D15/1000000 -> 3.50424 | E10: =Revenue_Forecast!E15/1000000 -> 10.7406 | F10: =Revenue_Forecast!F15/1000000 -> 24.57792 | G10: =Revenue_Forecast!G15/1000000 -> 48.96
B11: EBITDA ($M) | C11: =Revenue_Forecast!C37/1000000 -> -1.3519635 | D11: =Revenue_Forecast!D37/1000000 -> -1.3950072 | E11: =Revenue_Forecast!E37/1000000 -> -0.252294 | F11: =Revenue_Forecast!F37/1000000 -> 3.1020768 | G11: =Revenue_Forecast!G37/1000000 -> 11.1776
B35: Customer acquisition mix
B37: Channel | C37: Y1 mix % | D37: Y3 mix %
B38: Organic social | C38: =Acquisition_Mix!C8 -> 0.2 | D38: =Acquisition_Mix!D8 -> 0.16
B39: Influencer seeding | C39: =Acquisition_Mix!C9 -> 0.1 | D39: =Acquisition_Mix!D9 -> 0.14
B40: SEO content | C40: =Acquisition_Mix!C10 -> 0.08 | D40: =Acquisition_Mix!D10 -> 0.14
B41: Paid social | C41: =Acquisition_Mix!C11 -> 0.4 | D41: =Acquisition_Mix!D11 -> 0.3
B42: Partnerships | C42: =Acquisition_Mix!C12 -> 0.07 | D42: =Acquisition_Mix!D12 -> 0.12
B43: Referral program | C43: =Acquisition_Mix!C13 -> 0.1 | D43: =Acquisition_Mix!D13 -> 0.18
B44: Marketplaces | C44: =Acquisition_Mix!C14 -> 0.05 | D44: =Acquisition_Mix!D14 -> 0.06
B48: Gross margin & EBITDA margin trajectory
B50: Metric | C50: Year 1 | D50: Year 2 | E50: Year 3 | F50: Year 4 | G50: Year 5
B51: Gross margin | C51: =Revenue_Forecast!C25 -> 0.44 | D51: =Revenue_Forecast!D25 -> 0.47 | E51: =Revenue_Forecast!E25 -> 0.51 | F51: =Revenue_Forecast!F25 -> 0.54 | G51: =Revenue_Forecast!G25 -> 0.56
B52: EBITDA margin | C52: =Revenue_Forecast!C38 -> -1.4367428 | D52: =Revenue_Forecast!D38 -> -0.39809123 | E52: =Revenue_Forecast!E38 -> -0.023489749 | F52: =Revenue_Forecast!F38 -> 0.12621397 | G52: =Revenue_Forecast!G38 -> 0.22830065

Sheet Sources
B2: DATA PROVENANCE
B3: Sources & Citations
B4: Every external benchmark used in the model is cited here. Internal modeling assumptions are noted as 'Internal'.
B7: Topic | C7: Source | D7: URL | E7: Last verified
B8: Global 3D printing market size (2025: $30.55B; 2030: $76–88B; CAGR 20.8–23.5%) | C8: Grand View Research; PR Newswire | D8: https://www.grandviewresearch.com/industry-analysis/3d-printing-industry-analysis | E8: Apr 2026
B9: Tabletop miniatures market ($1.42B in 2024, 7.1% CAGR to $2.67B by 2033) | C9: Market Intelo / Growth Market Reports | D9: https://marketintelo.com/report/tabletop-miniatures-game-market | E9: Apr 2026
B10: Tabletop games market overall ($18.1B in 2024 → $30.8B by 2035, 4.95% CAGR) | C10: Market Research Future | D10: https://www.marketresearchfuture.com/reports/table-top-games-market-10297 | E10: Apr 2026
B11: E-commerce average CAC ($68–84 blended; $21–87 by category) | C11: Genesys Growth; Shopify; LoyaltyLion (2025–2026) | D11: https://genesysgrowth.com/blog/customer-acquisition-cost-benchmarks-for-marketing-leaders | E11: Apr 2026
B12: CAC by channel benchmarks (paid social, SEO, organic) | C12: Phoenix Strategy Group | D12: https://www.phoenixstrategy.group/blog/cac-benchmarks-by-channel-2025 | E12: Apr 2026
B13: DTC CAC range ($23 pet → $89 supplements → $400+ luxury) | C13: Shopify; Retainful | D13: https://www.shopify.com/blog/customer-acquisition-cost-by-industry | E13: Apr 2026
B14: LTV:CAC benchmark of 3:1 minimum, 3–4× target for DTC | C14: Phoenix Strategy Group; Razorpay | D14: https://razorpay.com/learn/customer-acquisition-cost/ | E14: Apr 2026
B15: E-commerce repeat purchase rate average (28.2%; range 20–40%) | C15: Mobiloud; Opensend | D15: https://www.mobiloud.com/blog/repeat-customer-rate-ecommerce | E15: Apr 2026
B16: Best-in-class repeat purchase rate with subscription (55%+) | C16: Mobiloud (citing Klaviyo/Chewy data) | D16: https://www.opensend.com/post/repeat-purchase-rate-ecommerce | E16: Apr 2026
B17: 5% retention increase = 25–95% profit lift | C17: Bain & Company; Harvard Business School | D17: https://www.envive.ai/post/customer-retention-in-ecommerce-statistics | E17: Apr 2026
B18: Customers willing to pay 30%+ for personalized experiences | C18: Deloitte 2024 Personalization Research | D18: https://www.deloittedigital.com/us/en/insights/perspective/personalization-customer-personas.html | E18: Apr 2026
... B28: Volume per object size (8/35/120/280 cm³) | C28: Internal — Thingiverse upload sample analysis | D28: Stratified sample of public 3D model sizes | E28: Apr 2026
B30: All third-party benchmarks were verified at the date shown. Industry reports are commonly paywalled — figures cited above appear in publicly available summaries from the publisher. For authoritative figures used in funding documents, purchase the underlying reports.
